opentelemetry/exporter/richconsole/__init__.py
opentelemetry/exporter/richconsole/version.py
opentelemetry_exporter_richconsole-0.60b1.dist-info/METADATA
opentelemetry_exporter_richconsole-0.60b1.dist-info/WHEEL
opentelemetry_exporter_richconsole-0.60b1.dist-info/RECORD
